pySpintax/__init__.py
pySpintax/pySpintax.py
pySpintax-2.0.dist-info/LICENCE
pySpintax-2.0.dist-info/METADATA
pySpintax-2.0.dist-info/WHEEL
pySpintax-2.0.dist-info/top_level.txt
pySpintax-2.0.dist-info/RECORD
