Metadata-Version: 2.1
Name: pySpintax
Version: 2.0
Summary: Simple Spintax Spinner
Home-page: https://github.com/1dragosh/pySpintax
Author: 1dragosh
Author-email: contact@1dragosh.me
License: UNKNOWN
Platform: UNKNOWN
Classifier: Programming Language :: Python :: 3
Classifier: License :: OSI Approved :: MIT License
Classifier: Operating System :: OS Independent
